pmatch/__init__.py
pmatch/enable_auto_import.py
pmatch/match_template.py
pmatch/pama_ast.py
pmatch/pama_compiler.py
pmatch/pama_decorators.py
pmatch/pama_importhook.py
pmatch/pattern_parser.py
pmatch/syntax_support.py
pyPMatch-0.1.2.dist-info/METADATA
pyPMatch-0.1.2.dist-info/RECORD
pyPMatch-0.1.2.dist-info/WHEEL
pyPMatch-0.1.2.dist-info/top_level.txt
