Metadata-Version: 2.1
Name: pyPMatch
Version: 0.1.2
Summary: Pattern Matching in Python
Home-page: https://github.com/Tobias-Kohn/pyPMatch
Author: Tobias Kohn
Author-email: kohnt@tobiaskohn.ch
License: UNKNOWN
Platform: UNKNOWN
Classifier: Programming Language :: Python :: 3
Classifier: License :: OSI Approved :: Apache Software License
Classifier: Operating System :: OS Independent
